fastapi_limiter/__init__.py
fastapi_limiter/depends.py
fastapi_limiter/py.typed
fastapi_limiter_tl-0.1.2.dist-info/LICENSE
fastapi_limiter_tl-0.1.2.dist-info/METADATA
fastapi_limiter_tl-0.1.2.dist-info/WHEEL
fastapi_limiter_tl-0.1.2.dist-info/RECORD
