Metadata-Version: 2.3
Name: fastapi-limiter-tl
Version: 0.1.2
Summary: A request rate limiter for fastapi
License: Apache2.0
Keywords: fastapi,limiter
Author: long2ice
Author-email: long2ice@gmail.com
Requires-Python: >=3.11,<4.0
Classifier: License :: Other/Proprietary License
Classifier: Programming Language :: Python :: 3
Classifier: Programming Language :: Python :: 3.11
Classifier: Programming Language :: Python :: 3.12
Classifier: Programming Language :: Python :: 3.13
Requires-Dist: fastapi
Requires-Dist: redis (>=4.2.0rc1)
Project-URL: Documentation, https://github.com/Ro0tk1t/fastapi-limiter
Project-URL: Homepage, https://github.com/Ro0tk1t/fastapi-limiter
Project-URL: Repository, https://github.com/Ro0tk1t/fastapi-limiter.git
